<?xml version="1.0" encoding="UTF-8" standalone="no"?>
<resources>
  <resource name="secretboss" type="RESOURCE"/>
  <resource name="hpbar" type="RESOURCE"/>
  <resource name="object182" type="RESOURCE"/>
  <resource name="object7" type="RESOURCE"/>
  <resource name="object22" type="RESOURCE"/>
  <resource name="object10" type="RESOURCE"/>
  <resource name="object11" type="RESOURCE"/>
  <resource name="object470" type="RESOURCE"/>
  <resource name="object17" type="RESOURCE"/>
  <resource name="object18" type="RESOURCE"/>
  <resource name="object12" type="RESOURCE"/>
  <resource name="object24" type="RESOURCE"/>
  <resource name="object158" type="RESOURCE"/>
  <resource name="object13" type="RESOURCE"/>
  <resource name="object480" type="RESOURCE"/>
  <resource name="object291" type="RESOURCE"/>
  <resource name="object292" type="RESOURCE"/>
  <resource name="object293" type="RESOURCE"/>
  <resource name="object294" type="RESOURCE"/>
  <resource name="object463" type="RESOURCE"/>
  <resource name="object465" type="RESOURCE"/>
  <resource name="object287" type="RESOURCE"/>
  <resource name="object290" type="RESOURCE"/>
  <resource name="object289" type="RESOURCE"/>
  <resource name="object288" type="RESOURCE"/>
  <resource name="object464" type="RESOURCE"/>
  <resource name="object466" type="RESOURCE"/>
  <resource name="object14" type="RESOURCE"/>
  <resource name="object31" type="RESOURCE"/>
  <resource name="objShadow" type="RESOURCE"/>
  <resource name="object27" type="RESOURCE"/>
  <resource name="object29" type="RESOURCE"/>
  <resource name="object149" type="RESOURCE"/>
  <resource name="object150" type="RESOURCE"/>
  <resource name="object151" type="RESOURCE"/>
  <resource name="object152" type="RESOURCE"/>
  <resource name="object153" type="RESOURCE"/>
  <resource name="object156" type="RESOURCE"/>
  <resource name="object159" type="RESOURCE"/>
  <resource name="object8" type="RESOURCE"/>
  <resource name="object23" type="RESOURCE"/>
  <resource name="object178" type="RESOURCE"/>
  <resource name="主角z" type="GROUP"/>
  <resource name="siwang2" type="RESOURCE"/>
  <resource name="object458" type="RESOURCE"/>
  <resource name="object457" type="RESOURCE"/>
  <resource name="object445" type="RESOURCE"/>
  <resource name="object459" type="RESOURCE"/>
  <resource name="object462" type="RESOURCE"/>
  <resource name="object469" type="RESOURCE"/>
  <resource name="object468" type="RESOURCE"/>
  <resource name="object460" type="RESOURCE"/>
  <resource name="object467" type="RESOURCE"/>
  <resource name="object461" type="RESOURCE"/>
</resources>
