<?xml version="1.0" encoding="UTF-8" standalone="no"?>
<event category="CREATE" id="0">
  <actions>
    <action id="301" library="1">
      <!--action name: Set_Alarm-->
      <kind>NORMAL</kind>
      <allowRelative>true</allowRelative>
      <question>false</question>
      <canApplyTo>true</canApplyTo>
      <actionType>FUNCTION</actionType>
      <functionName>action_set_alarm</functionName>
      <relative>false</relative>
      <not>false</not>
      <appliesTo>.self</appliesTo>
      <arguments>
        <argument kind="EXPRESSION">1</argument>
        <argument kind="MENU">10</argument>
      </arguments>
    </action>
    <action id="301" library="1">
      <!--action name: Set_Alarm-->
      <kind>NORMAL</kind>
      <allowRelative>true</allowRelative>
      <question>false</question>
      <canApplyTo>true</canApplyTo>
      <actionType>FUNCTION</actionType>
      <functionName>action_set_alarm</functionName>
      <relative>false</relative>
      <not>false</not>
      <appliesTo>.self</appliesTo>
      <arguments>
        <argument kind="EXPRESSION">1</argument>
        <argument kind="MENU">3</argument>
      </arguments>
    </action>
    <action id="301" library="1">
      <!--action name: Set_Alarm-->
      <kind>NORMAL</kind>
      <allowRelative>true</allowRelative>
      <question>false</question>
      <canApplyTo>true</canApplyTo>
      <actionType>FUNCTION</actionType>
      <functionName>action_set_alarm</functionName>
      <relative>false</relative>
      <not>false</not>
      <appliesTo>.self</appliesTo>
      <arguments>
        <argument kind="EXPRESSION">1</argument>
        <argument kind="MENU">2</argument>
      </arguments>
    </action>
    <action id="603" library="1">
      <!--action name: Code-->
      <kind>CODE</kind>
      <allowRelative>false</allowRelative>
      <question>false</question>
      <canApplyTo>true</canApplyTo>
      <actionType>CODE</actionType>
      <functionName/>
      <relative>false</relative>
      <not>false</not>
      <appliesTo>.self</appliesTo>
      <arguments>
        <argument kind="STRING">maxHp = 100
nowHp = maxHp
maxBp = 100
nowBp = 100
image_speed = 0.3
attacking = 0
alarm[1] = 0
maxsta = 400
nowsta = 10
maxdef = 400
nowdef = 10
maxlv = 60
nowlv = 1
maxmp = 100
nowmp = maxmp
maxexp = 33570
nowexp = 0
shadow = 0
shadow_timer = 0
alarm[6]=0
instance_create(x,y,yingz)
</argument>
      </arguments>
    </action>
  </actions>
</event>
